odoo/addons/endpoint_product_catalog/README.rst
odoo/addons/endpoint_product_catalog/__init__.py
odoo/addons/endpoint_product_catalog/__manifest__.py
odoo/addons/endpoint_product_catalog/i18n/endpoint_product_catalog.pot
odoo/addons/endpoint_product_catalog/i18n/it.po
odoo/addons/endpoint_product_catalog/models/__init__.py
odoo/addons/endpoint_product_catalog/models/endpoint_endpoint.py
odoo/addons/endpoint_product_catalog/models/ir_filters.py
odoo/addons/endpoint_product_catalog/readme/CONTRIBUTORS.md
odoo/addons/endpoint_product_catalog/readme/DESCRIPTION.md
odoo/addons/endpoint_product_catalog/readme/USAGE.md
odoo/addons/endpoint_product_catalog/static/description/icon.png
odoo/addons/endpoint_product_catalog/static/description/index.html
odoo/addons/endpoint_product_catalog/views/endpoint_endpoint.xml
odoo/addons/endpoint_product_catalog/views/ir_filters.xml
odoo_addon_endpoint_product_catalog-18.0.1.0.0.2.dist-info/METADATA
odoo_addon_endpoint_product_catalog-18.0.1.0.0.2.dist-info/WHEEL
odoo_addon_endpoint_product_catalog-18.0.1.0.0.2.dist-info/top_level.txt
odoo_addon_endpoint_product_catalog-18.0.1.0.0.2.dist-info/RECORD
