Metadata-Version: 2.1
Name: odoo-addon-endpoint_product_catalog
Version: 18.0.1.0.0.2
Requires-Python: >=3.10
Requires-Dist: odoo-addon-endpoint==18.0.*
Requires-Dist: odoo-addon-product_assortment==18.0.*
Requires-Dist: odoo==18.0.*
Summary: Handle endpoints for product catalogs
Home-page: https://github.com/OCA/web-api-contrib
License: AGPL-3
Author: Camptocamp, Odoo Community Association (OCA)
Author-email: support@odoo-community.org
Classifier: Programming Language :: Python
Classifier: Framework :: Odoo
Classifier: Framework :: Odoo :: 18.0
Classifier: License :: OSI Approved :: GNU Affero General Public License v3
